pytaridx/__init__.py
pytaridx/block.py
pytaridx/blocktree.py
pytaridx/main.py
pytaridx/pytaridx.py
pytaridx/reindex.py
pytaridx-1.0.2.dist-info/LICENSE
pytaridx-1.0.2.dist-info/METADATA
pytaridx-1.0.2.dist-info/NOTICE
pytaridx-1.0.2.dist-info/WHEEL
pytaridx-1.0.2.dist-info/entry_points.txt
pytaridx-1.0.2.dist-info/top_level.txt
pytaridx-1.0.2.dist-info/RECORD
