Metadata-Version: 2.1
Name: pytaridx
Version: 1.0.2
Summary: A package for creating, reading from, and writing to indexed tar archives.
Home-page: https://github.com/LLNL/pytaridx
Author: Tomas Oppelstrup
Author-email: oppelstrup2@llnl.gov
License: MIT
Platform: UNKNOWN
Classifier: Development Status :: 4 - Beta
Classifier: License :: OSI Approved :: MIT License
Classifier: Intended Audience :: Developers
Classifier: Operating System :: Unix
Classifier: Programming Language :: Python
Classifier: Programming Language :: Python :: 2.7
Classifier: Programming Language :: Python :: 3
Classifier: Programming Language :: Python :: 3.5
Classifier: Programming Language :: Python :: 3.6
Classifier: Programming Language :: Python :: 3.7
License-File: LICENSE
License-File: NOTICE
